Metadata-Version: 2.1
Name: fewsver
Version: 0.1.0
Summary: Package for verifying GLOFFIS streamflow forecasts.
Home-page: UNKNOWN
Author: Georgios Boumis
Author-email: boumis.georgios@gmail.com
License: UNKNOWN
Platform: UNKNOWN
Classifier: Programming Language :: Python :: 3
Classifier: License :: OSI Approved :: MIT License
Classifier: Operating System :: OS Independent
